{"cameraMode":{"drawMode":0,"name":"Shaded","section":"Shading Mode"},"sceneLighting":true,"audioPlay":false,"sceneViewState":{"m_AlwaysRefresh":false,"showFog":true,"showSkybox":true,"showFlares":true,"showImageEffects":true,"showParticleSystems":true,"showVisualEffectGraphs":true,"m_FxEnabled":true},"in2DMode":false,"pivot":{"x":-5.606543064117432,"y":3.04813814163208,"z":-3.1104214191436769},"rotation":{"x":-0.5121214985847473,"y":-0.1667138934135437,"z":0.1019827276468277,"w":-0.8365607857704163},"size":6.609219074249268,"orthographic":false}